{
  "aggregate": {
    "counters": {
      "vusers.created_by_name.Name origin": 300,
      "vusers.created": 300,
      "http.requests": 300,
      "http.codes.200": 300,
      "http.responses": 300,
      "vusers.failed": 0,
      "vusers.completed": 300
    },
    "rates": {
      "http.request_rate": 5
    },
    "firstCounterAt": 1665040022418,
    "firstHistogramAt": 1665040022822,
    "lastCounterAt": 1665040084008,
    "lastHistogramAt": 1665040084008,
    "firstMetricAt": 1665040022418,
    "lastMetricAt": 1665040084008,
    "period": 1665040080000,
    "summaries": {
      "http.response_time": {
        "min": 84,
        "max": 123,
        "count": 300,
        "p50": 94.6,
        "median": 94.6,
        "p75": 96.6,
        "p90": 96.6,
        "p95": 98.5,
        "p99": 98.5,
        "p999": 98.5
      },
      "vusers.session_length": {
        "min": 2334.4,
        "max": 2409.8,
        "count": 300,
        "p50": 2369,
        "median": 2369,
        "p75": 2369,
        "p90": 2369,
        "p95": 2369,
        "p99": 2416.8,
        "p999": 2416.8
      }
    },
    "histograms": {
      "http.response_time": {
        "min": 84,
        "max": 123,
        "count": 300,
        "p50": 94.6,
        "median": 94.6,
        "p75": 96.6,
        "p90": 96.6,
        "p95": 98.5,
        "p99": 98.5,
        "p999": 98.5
      },
      "vusers.session_length": {
        "min": 2334.4,
        "max": 2409.8,
        "count": 300,
        "p50": 2369,
        "median": 2369,
        "p75": 2369,
        "p90": 2369,
        "p95": 2369,
        "p99": 2416.8,
        "p999": 2416.8
      }
    }
  },
  "intermediate": [
    {
      "counters": {
        "vusers.created_by_name.Name origin": 40,
        "vusers.created": 40,
        "http.requests": 40,
        "http.codes.200": 40,
        "http.responses": 40,
        "vusers.failed": 0,
        "vusers.completed": 30
      },
      "rates": {
        "http.request_rate": 5
      },
      "http.request_rate": null,
      "firstCounterAt": 1665040022418,
      "firstHistogramAt": 1665040022822,
      "lastCounterAt": 1665040029991,
      "lastHistogramAt": 1665040029991,
      "firstMetricAt": 1665040022418,
      "lastMetricAt": 1665040029991,
      "period": "1665040020000",
      "summaries": {
        "http.response_time": {
          "min": 84,
          "max": 99,
          "count": 40,
          "p50": 92.8,
          "median": 92.8,
          "p75": 94.6,
          "p90": 96.6,
          "p95": 96.6,
          "p99": 98.5,
          "p999": 98.5
        },
        "vusers.session_length": {
          "min": 2334.4,
          "max": 2409.8,
          "count": 30,
          "p50": 2369,
          "median": 2369,
          "p75": 2369,
          "p90": 2369,
          "p95": 2416.8,
          "p99": 2416.8,
          "p999": 2416.8
        }
      },
      "histograms": {
        "http.response_time": {
          "min": 84,
          "max": 99,
          "count": 40,
          "p50": 92.8,
          "median": 92.8,
          "p75": 94.6,
          "p90": 96.6,
          "p95": 96.6,
          "p99": 98.5,
          "p999": 98.5
        },
        "vusers.session_length": {
          "min": 2334.4,
          "max": 2409.8,
          "count": 30,
          "p50": 2369,
          "median": 2369,
          "p75": 2369,
          "p90": 2369,
          "p95": 2416.8,
          "p99": 2416.8,
          "p999": 2416.8
        }
      }
    },
    {
      "counters": {
        "vusers.created_by_name.Name origin": 50,
        "vusers.created": 50,
        "http.requests": 50,
        "http.codes.200": 50,
        "http.responses": 50,
        "vusers.failed": 0,
        "vusers.completed": 50
      },
      "rates": {
        "http.request_rate": 5
      },
      "http.request_rate": null,
      "firstCounterAt": 1665040030417,
      "firstHistogramAt": 1665040030771,
      "lastCounterAt": 1665040039998,
      "lastHistogramAt": 1665040039998,
      "firstMetricAt": 1665040030417,
      "lastMetricAt": 1665040039998,
      "period": "1665040030000",
      "summaries": {
        "http.response_time": {
          "min": 85,
          "max": 123,
          "count": 50,
          "p50": 94.6,
          "median": 94.6,
          "p75": 96.6,
          "p90": 96.6,
          "p95": 96.6,
          "p99": 98.5,
          "p999": 98.5
        },
        "vusers.session_length": {
          "min": 2342.6,
          "max": 2405.1,
          "count": 50,
          "p50": 2369,
          "median": 2369,
          "p75": 2369,
          "p90": 2369,
          "p95": 2369,
          "p99": 2369,
          "p999": 2369
        }
      },
      "histograms": {
        "http.response_time": {
          "min": 85,
          "max": 123,
          "count": 50,
          "p50": 94.6,
          "median": 94.6,
          "p75": 96.6,
          "p90": 96.6,
          "p95": 96.6,
          "p99": 98.5,
          "p999": 98.5
        },
        "vusers.session_length": {
          "min": 2342.6,
          "max": 2405.1,
          "count": 50,
          "p50": 2369,
          "median": 2369,
          "p75": 2369,
          "p90": 2369,
          "p95": 2369,
          "p99": 2369,
          "p999": 2369
        }
      }
    },
    {
      "counters": {
        "vusers.created_by_name.Name origin": 50,
        "vusers.created": 50,
        "http.requests": 50,
        "http.codes.200": 49,
        "http.responses": 49,
        "vusers.failed": 0,
        "vusers.completed": 49
      },
      "rates": {
        "http.request_rate": 5
      },
      "http.request_rate": null,
      "firstCounterAt": 1665040040417,
      "firstHistogramAt": 1665040040789,
      "lastCounterAt": 1665040049958,
      "lastHistogramAt": 1665040049958,
      "firstMetricAt": 1665040040417,
      "lastMetricAt": 1665040049958,
      "period": "1665040040000",
      "summaries": {
        "http.response_time": {
          "min": 86,
          "max": 98,
          "count": 49,
          "p50": 94.6,
          "median": 94.6,
          "p75": 96.6,
          "p90": 96.6,
          "p95": 96.6,
          "p99": 96.6,
          "p999": 96.6
        },
        "vusers.session_length": {
          "min": 2347.1,
          "max": 2391.3,
          "count": 49,
          "p50": 2369,
          "median": 2369,
          "p75": 2369,
          "p90": 2369,
          "p95": 2369,
          "p99": 2369,
          "p999": 2369
        }
      },
      "histograms": {
        "http.response_time": {
          "min": 86,
          "max": 98,
          "count": 49,
          "p50": 94.6,
          "median": 94.6,
          "p75": 96.6,
          "p90": 96.6,
          "p95": 96.6,
          "p99": 96.6,
          "p999": 96.6
        },
        "vusers.session_length": {
          "min": 2347.1,
          "max": 2391.3,
          "count": 49,
          "p50": 2369,
          "median": 2369,
          "p75": 2369,
          "p90": 2369,
          "p95": 2369,
          "p99": 2369,
          "p999": 2369
        }
      }
    },
    {
      "counters": {
        "vusers.created_by_name.Name origin": 50,
        "vusers.created": 50,
        "http.requests": 50,
        "http.codes.200": 51,
        "http.responses": 51,
        "vusers.failed": 0,
        "vusers.completed": 50
      },
      "rates": {
        "http.request_rate": 5
      },
      "http.request_rate": null,
      "firstCounterAt": 1665040050004,
      "firstHistogramAt": 1665040050004,
      "lastCounterAt": 1665040059984,
      "lastHistogramAt": 1665040059984,
      "firstMetricAt": 1665040050004,
      "lastMetricAt": 1665040059984,
      "period": "1665040050000",
      "summaries": {
        "http.response_time": {
          "min": 84,
          "max": 98,
          "count": 51,
          "p50": 92.8,
          "median": 92.8,
          "p75": 96.6,
          "p90": 98.5,
          "p95": 98.5,
          "p99": 98.5,
          "p999": 98.5
        },
        "vusers.session_length": {
          "min": 2334.5,
          "max": 2391.9,
          "count": 50,
          "p50": 2369,
          "median": 2369,
          "p75": 2369,
          "p90": 2369,
          "p95": 2369,
          "p99": 2369,
          "p999": 2369
        }
      },
      "histograms": {
        "http.response_time": {
          "min": 84,
          "max": 98,
          "count": 51,
          "p50": 92.8,
          "median": 92.8,
          "p75": 96.6,
          "p90": 98.5,
          "p95": 98.5,
          "p99": 98.5,
          "p999": 98.5
        },
        "vusers.session_length": {
          "min": 2334.5,
          "max": 2391.9,
          "count": 50,
          "p50": 2369,
          "median": 2369,
          "p75": 2369,
          "p90": 2369,
          "p95": 2369,
          "p99": 2369,
          "p999": 2369
        }
      }
    },
    {
      "counters": {
        "vusers.created_by_name.Name origin": 50,
        "vusers.created": 50,
        "http.requests": 50,
        "http.codes.200": 50,
        "http.responses": 50,
        "vusers.failed": 0,
        "vusers.completed": 51
      },
      "rates": {
        "http.request_rate": 5
      },
      "http.request_rate": null,
      "firstCounterAt": 1665040060009,
      "firstHistogramAt": 1665040060009,
      "lastCounterAt": 1665040069998,
      "lastHistogramAt": 1665040069998,
      "firstMetricAt": 1665040060009,
      "lastMetricAt": 1665040069998,
      "period": "1665040060000",
      "summaries": {
        "http.response_time": {
          "min": 86,
          "max": 99,
          "count": 50,
          "p50": 92.8,
          "median": 92.8,
          "p75": 94.6,
          "p90": 96.6,
          "p95": 96.6,
          "p99": 96.6,
          "p999": 96.6
        },
        "vusers.session_length": {
          "min": 2344.3,
          "max": 2388,
          "count": 51,
          "p50": 2369,
          "median": 2369,
          "p75": 2369,
          "p90": 2369,
          "p95": 2369,
          "p99": 2369,
          "p999": 2369
        }
      },
      "histograms": {
        "http.response_time": {
          "min": 86,
          "max": 99,
          "count": 50,
          "p50": 92.8,
          "median": 92.8,
          "p75": 94.6,
          "p90": 96.6,
          "p95": 96.6,
          "p99": 96.6,
          "p999": 96.6
        },
        "vusers.session_length": {
          "min": 2344.3,
          "max": 2388,
          "count": 51,
          "p50": 2369,
          "median": 2369,
          "p75": 2369,
          "p90": 2369,
          "p95": 2369,
          "p99": 2369,
          "p999": 2369
        }
      }
    },
    {
      "counters": {
        "vusers.created_by_name.Name origin": 50,
        "vusers.created": 50,
        "http.requests": 50,
        "vusers.failed": 0,
        "vusers.completed": 50,
        "http.codes.200": 49,
        "http.responses": 49
      },
      "rates": {
        "http.request_rate": 5
      },
      "http.request_rate": null,
      "firstCounterAt": 1665040070417,
      "firstHistogramAt": 1665040070784,
      "lastCounterAt": 1665040079999,
      "lastHistogramAt": 1665040079999,
      "firstMetricAt": 1665040070417,
      "lastMetricAt": 1665040079999,
      "period": "1665040070000",
      "summaries": {
        "vusers.session_length": {
          "min": 2346.2,
          "max": 2385.1,
          "count": 50,
          "p50": 2369,
          "median": 2369,
          "p75": 2369,
          "p90": 2369,
          "p95": 2369,
          "p99": 2369,
          "p999": 2369
        },
        "http.response_time": {
          "min": 86,
          "max": 98,
          "count": 49,
          "p50": 94.6,
          "median": 94.6,
          "p75": 96.6,
          "p90": 96.6,
          "p95": 96.6,
          "p99": 98.5,
          "p999": 98.5
        }
      },
      "histograms": {
        "vusers.session_length": {
          "min": 2346.2,
          "max": 2385.1,
          "count": 50,
          "p50": 2369,
          "median": 2369,
          "p75": 2369,
          "p90": 2369,
          "p95": 2369,
          "p99": 2369,
          "p999": 2369
        },
        "http.response_time": {
          "min": 86,
          "max": 98,
          "count": 49,
          "p50": 94.6,
          "median": 94.6,
          "p75": 96.6,
          "p90": 96.6,
          "p95": 96.6,
          "p99": 98.5,
          "p999": 98.5
        }
      }
    }
  ]
}